django_testcase_generator/__init__.py
django_testcase_generator/management/__init__.py
django_testcase_generator/management/commands/__init__.py
django_testcase_generator/management/commands/generate_tests.py
django_testcase_generator/tests/__init__.py
django_testcase_generator-0.1.0.dist-info/LICENSE
django_testcase_generator-0.1.0.dist-info/METADATA
django_testcase_generator-0.1.0.dist-info/WHEEL
django_testcase_generator-0.1.0.dist-info/top_level.txt
django_testcase_generator-0.1.0.dist-info/RECORD
