Metadata-Version: 2.1
Name: django-testcase-generator
Version: 0.1.0
Summary: A Django app to generate test cases from urls.py.
Home-page: https://github.com/arifbd2221/django_testcase_generator
Author: Mohidul Hoque Arif
Author-email: mohidulhoque216@gmail.com
License: MIT
Keywords: django,tests,unittest,django-rest-framework
Platform: UNKNOWN
Classifier: Framework :: Django
Classifier: Programming Language :: Python :: 3
Classifier: License :: OSI Approved :: MIT License
Requires-Dist: Django (>=2.2)
Requires-Dist: djangorestframework
